{"n_topics": 4, "topics": [[{"word": "file", "probability": 0.009525}, {"word": "window", "probability": 0.007474}, {"word": "system", "probability": 0.007193}, {"word": "program", "probability": 0.005893}, {"word": "image", "probability": 0.005751}, {"word": "drive", "probability": 0.005628}, {"word": "work", "probability": 0.005619}, {"word": "run", "probability": 0.005354}, {"word": "problem", "probability": 0.004807}, {"word": "software", "probability": 0.004601}], [{"word": "god", "probability": 0.01098}, {"word": "people", "probability": 0.009287}, {"word": "say", "probability": 0.007217}, {"word": "come", "probability": 0.004944}, {"word": "believe", "probability": 0.004672}, {"word": "time", "probability": 0.004292}, {"word": "man", "probability": 0.004079}, {"word": "christian", "probability": 0.004014}, {"word": "way", "probability": 0.0038}, {"word": "jesus", "probability": 0.003715}], [{"word": "people", "probability": 0.006255}, {"word": "time", "probability": 0.004809}, {"word": "right", "probability": 0.004174}, {"word": "government", "probability": 0.00376}, {"word": "say", "probability": 0.003744}, {"word": "good", "probability": 0.003704}, {"word": "work", "probability": 0.003461}, {"word": "year", "probability": 0.003455}, {"word": "key", "probability": 0.003407}, {"word": "thing", "probability": 0.003385}], [{"word": "game", "probability": 0.010402}, {"word": "year", "probability": 0.00826}, {"word": "team", "probability": 0.007109}, {"word": "good", "probability": 0.006681}, {"word": "play", "probability": 0.005378}, {"word": "space", "probability": 0.005153}, {"word": "win", "probability": 0.004918}, {"word": "player", "probability": 0.00452}, {"word": "time", "probability": 0.004507}, {"word": "get", "probability": 0.004114}]]}